uggo/__init__.py
uggo/barchart.py
uggo/chart.py
uggo/linechart.py
uggo/piechart.py
uggo-0.1.dist-info/LICENSE
uggo-0.1.dist-info/METADATA
uggo-0.1.dist-info/WHEEL
uggo-0.1.dist-info/top_level.txt
uggo-0.1.dist-info/RECORD
