Metadata-Version: 2.1
Name: uggo
Version: 0.1
Summary: Tastefully ugly charts in Python
Home-page: https://github.com/matthewwiese/uggo
Author: Matt Wiese
Author-email: uggo@mattwie.se
Classifier: Programming Language :: Python :: 3
Classifier: License :: OSI Approved :: MIT License
Classifier: Operating System :: OS Independent
License-File: LICENSE
Requires-Dist: pillow >=10.4.0
